tensorforce/__init__.py
tensorforce/exception.py
tensorforce/util.py
tensorforce/agents/__init__.py
tensorforce/agents/a2c.py
tensorforce/agents/ac.py
tensorforce/agents/agent.py
tensorforce/agents/constant.py
tensorforce/agents/double_dqn.py
tensorforce/agents/dpg.py
tensorforce/agents/dqn.py
tensorforce/agents/dueling_dqn.py
tensorforce/agents/ppo.py
tensorforce/agents/random.py
tensorforce/agents/recorder.py
tensorforce/agents/tensorforce.py
tensorforce/agents/trpo.py
tensorforce/agents/vpg.py
tensorforce/core/__init__.py
tensorforce/core/config.py
tensorforce/core/module.py
tensorforce/core/distributions/__init__.py
tensorforce/core/distributions/bernoulli.py
tensorforce/core/distributions/beta.py
tensorforce/core/distributions/categorical.py
tensorforce/core/distributions/distribution.py
tensorforce/core/distributions/gaussian.py
tensorforce/core/layers/__init__.py
tensorforce/core/layers/attention.py
tensorforce/core/layers/convolution.py
tensorforce/core/layers/dense.py
tensorforce/core/layers/embedding.py
tensorforce/core/layers/input_rnn.py
tensorforce/core/layers/keras.py
tensorforce/core/layers/layer.py
tensorforce/core/layers/linear.py
tensorforce/core/layers/misc.py
tensorforce/core/layers/normalization.py
tensorforce/core/layers/pooling.py
tensorforce/core/layers/preprocessing.py
tensorforce/core/layers/rnn.py
tensorforce/core/memories/__init__.py
tensorforce/core/memories/memory.py
tensorforce/core/memories/queue.py
tensorforce/core/memories/recent.py
tensorforce/core/memories/replay.py
tensorforce/core/models/__init__.py
tensorforce/core/models/constant.py
tensorforce/core/models/model.py
tensorforce/core/models/random.py
tensorforce/core/models/tensorforce.py
tensorforce/core/networks/__init__.py
tensorforce/core/networks/auto.py
tensorforce/core/networks/keras.py
tensorforce/core/networks/network.py
tensorforce/core/networks/preprocessor.py
tensorforce/core/objectives/__init__.py
tensorforce/core/objectives/deterministic_policy_gradient.py
Tensorforce-0.6.5.dist-info/LICENSE
Tensorforce-0.6.5.dist-info/METADATA
Tensorforce-0.6.5.dist-info/WHEEL
Tensorforce-0.6.5.dist-info/top_level.txt
Tensorforce-0.6.5.dist-info/RECORD
