Metadata-Version: 2.1
Name: Tensorforce
Version: 0.6.5
Summary: Tensorforce: a TensorFlow library for applied reinforcement learning
Home-page: http://github.com/tensorforce/tensorforce
Author: Alexander Kuhnle
Author-email: tensorforce.team@gmail.com
License: Apache 2.0
Download-URL: https://github.com/tensorforce/tensorforce/archive/0.6.5.tar.gz
Platform: UNKNOWN
Classifier: Natural Language :: English
Classifier: Topic :: Scientific/Engineering
Classifier: Programming Language :: Python :: 3
Classifier: Programming Language :: Python :: 3.6
Classifier: Programming Language :: Python :: 3.7
Classifier: Programming Language :: Python :: 3.8
Requires-Python: >=3.5
License-File: LICENSE
Requires-Dist: gym (>=0.19.0)
Requires-Dist: h5py (~=3.1.0)
Requires-Dist: matplotlib (>=3.3.4)
Requires-Dist: msgpack (>=1.0.2)
Requires-Dist: msgpack-numpy (>=0.4.7.1)
Requires-Dist: numpy (==1.19.5)
Requires-Dist: Pillow (>=8.3.1)
Requires-Dist: tensorflow (==2.6.0)
Requires-Dist: tqdm (>=4.62.2)
Provides-Extra: ale
Requires-Dist: ale-py (>=0.7rc4) ; extra == 'ale'
Provides-Extra: carla
Requires-Dist: pygame ; extra == 'carla'
Requires-Dist: opencv-python ; extra == 'carla'
Provides-Extra: docs
Requires-Dist: m2r (>=0.2.1) ; extra == 'docs'
Requires-Dist: recommonmark (>=0.7.1) ; extra == 'docs'
Requires-Dist: sphinx (>=4.0.2) ; extra == 'docs'
Requires-Dist: sphinx-rtd-theme (>=0.5.2) ; extra == 'docs'
Provides-Extra: envs
Requires-Dist: ale-py ; extra == 'envs'
Requires-Dist: gym[atari,box2d,classic_control] (>=0.18.3) ; extra == 'envs'
Requires-Dist: box2d (>=2.3.10) ; extra == 'envs'
Requires-Dist: gym-retro (>=0.8.0) ; extra == 'envs'
Requires-Dist: vizdoom (==1.1.7) ; extra == 'envs'
Provides-Extra: gym
Requires-Dist: gym[box2d,classic_control] (>=0.19.0) ; extra == 'gym'
Requires-Dist: box2d (>=2.3.10) ; extra == 'gym'
Provides-Extra: retro
Requires-Dist: gym-retro (>=0.8.0) ; extra == 'retro'
Provides-Extra: tests
Requires-Dist: pytest (>=6.2.4) ; extra == 'tests'
Provides-Extra: tfa
Requires-Dist: tensorflow-addons (>=0.14.0) ; extra == 'tfa'
Provides-Extra: tune
Requires-Dist: hpbandster (>=0.7.4) ; extra == 'tune'
Provides-Extra: vizdoom
Requires-Dist: vizdoom (>=1.1.8) ; extra == 'vizdoom'
